[
    {
        "year": "732",
        "content": "查理·马特率领的法兰克军队在图尔战役中击败拉赫曼率领的倭马亚军队。",
        "type": "event"
    },
    {
        "year": "1780",
        "content": "历史上最致命的大西洋飓风袭击加勒比海地区，最终共造成至少22,000人死亡。",
        "type": "event"
    },
    {
        "year": "1841",
        "content": "第一次鸦片战争：英国军队攻占镇海。",
        "type": "event"
    },
    {
        "year": "1846",
        "content": "英国天文学家威廉·拉塞尔发现海王星最大的卫星海卫一，并首次提及海王星环。",
        "type": "event"
    },
    {
        "year": "1868",
        "content": "古巴独立运动领袖塞斯佩德斯宣布古巴脱离西班牙独立，十年战争爆发。",
        "type": "event"
    },
    {
        "year": "1911",
        "content": "中国湖北省武昌革命组织文学社和共进会发动武昌起义，随后演变为推翻清朝政府的辛亥革命；因中国各地革命行动成功，孙中山回中国肇建了中华民国，形成孙中山领导的南京政府及清朝袁世凯的北京政府南北对峙，直到袁世凯翌年逼清帝退位，中华民国始取代清朝。",
        "type": "event"
    },
    {
        "year": "1913",
        "content": "巴拿马运河竣工。",
        "type": "event"
    },
    {
        "year": "1919",
        "content": "中华革命党改组为中国国民党，由孙中山总理绝对领导。",
        "type": "event"
    },
    {
        "year": "1924",
        "content": "孙中山所领导的广州军政府出兵镇压广州商团事变。",
        "type": "event"
    },
    {
        "year": "1925",
        "content": "故宫博物院于双十国庆日，在中华民国北平市（今中国北京市）正式开馆。",
        "type": "event"
    },
    {
        "year": "1926",
        "content": "国民革命军北伐：国民革命军占领武昌。",
        "type": "event"
    },
    {
        "year": "1928",
        "content": "蒋中正被任命成为国民政府主席及军事委员会委员长，并在之后掌握中国国民党、中华民国政府和中华民国国军等三位一体之党政军权力，至1975年逝世为止。",
        "type": "event"
    },
    {
        "year": "1933",
        "content": "拉丁美洲国家签署《萨维德拉·拉马斯互不侵犯条约》",
        "type": "event"
    },
    {
        "year": "1934",
        "content": "蒋中正开始第五次剿共，中国工农红军开始长征。",
        "type": "event"
    },
    {
        "year": "1935",
        "content": "大日本帝国在台湾举办始政四十周年纪念台湾博览会。",
        "type": "event"
    },
    {
        "year": "1937",
        "content": "中国抗日战争：中国工农红军南方八省游击队改编为新四军。",
        "type": "event"
    },
    {
        "year": "1938",
        "content": "中国抗日战争：日军在广东大亚湾登陆，开始进攻广州。",
        "type": "event"
    },
    {
        "year": "1938",
        "content": "中国抗日战争：万家岭战役结束，中华民国军队歼灭日军第106师团主力大部。",
        "type": "event"
    },
    {
        "year": "1943",
        "content": "侵占新加坡的大日本帝国陆军宪兵队肆意逮捕、拷问57名平民，导致15人死于樟宜监狱，史称“双十节事件”。",
        "type": "event"
    },
    {
        "year": "1943",
        "content": "在日本占领北婆罗洲时期的日本鬼子在当地抓壮丁要求加入宪兵队行列，以郭横南同志为首的“神山游击队”成立了！并且发动了“哲斯顿起义”，但是最终在太平洋战争末期的1944年1月末以起义失败告终。史称为“双十起义”。",
        "type": "event"
    },
    {
        "year": "1945",
        "content": "中华民国国民政府暨中国国民党代表王世杰等人和中国共产党代表周恩来等人在重庆签署《双十协定》。",
        "type": "event"
    },
    {
        "year": "1945",
        "content": "朝鲜共产党中央组织委员会成立。",
        "type": "event"
    },
    {
        "year": "1956",
        "content": "香港发生双十暴动，警民冲突主要地点在九龙西部及荃湾一带，局势要两天后才逐渐平息，共造成59人死亡，乃香港开埠以来死伤最严重之社会骚动事件。",
        "type": "event"
    },
    {
        "year": "1962",
        "content": "台湾第一家电视台台湾电视公司开播。",
        "type": "event"
    },
    {
        "year": "1963",
        "content": "《部分禁止核试验条约》生效。",
        "type": "event"
    },
    {
        "year": "1964",
        "content": "第18届奥运会在日本东京开幕。",
        "type": "event"
    },
    {
        "year": "1967",
        "content": "《外层空间条约》生效。",
        "type": "event"
    },
    {
        "year": "1970",
        "content": "斐济殖民地从英国独立，国号「斐济自治领」。",
        "type": "event"
    },
    {
        "year": "1973",
        "content": "美国副总统斯皮罗·阿格纽因涉嫌逃税而宣布辞职，为美国历史上唯一因丑闻辞职的副总统。",
        "type": "event"
    },
    {
        "year": "1975",
        "content": "巴布亚新几内亚从澳大利亚联邦独立，并加入联合国及英联邦王国。",
        "type": "event"
    },
    {
        "year": "1976",
        "content": "时任台湾省政府主席谢东闵被台湾独立运动参与者王幸男的炸弹炸伤，成为中华民国迄今唯一在任内遭遇暗杀的省主席。",
        "type": "event"
    },
    {
        "year": "2010",
        "content": "荷属安地列斯正式解体，其中库拉索与荷属圣马丁成为荷兰王国的构成国。",
        "type": "event"
    },
    {
        "year": "1567",
        "content": "卡特琳娜·米盖拉，西班牙公主（1597年逝世）",
        "type": "birth"
    },
    {
        "year": "1813",
        "content": "朱塞佩·威尔第，意大利歌剧作曲家（1901年逝世）",
        "type": "birth"
    },
    {
        "year": "1825",
        "content": "保罗·克鲁格，南非政治人物，第3任川斯瓦共和国总统（1904年逝世）",
        "type": "birth"
    },
    {
        "year": "1828",
        "content": "塞缪尔·J·兰德尔，美国政治家（1890年逝世）",
        "type": "birth"
    },
    {
        "year": "1830",
        "content": "伊莎贝拉二世，西班牙女王（1904年逝世）",
        "type": "birth"
    },
    {
        "year": "1835",
        "content": "慈禧太后，清文宗咸丰皇帝的妃子（1908年逝世）",
        "type": "birth"
    },
    {
        "year": "1889",
        "content": "汉·范米格伦，荷兰画家（1947年逝世）",
        "type": "birth"
    },
    {
        "year": "1892",
        "content": "伊沃·安德里奇，塞尔维亚作家（1975年逝世）",
        "type": "birth"
    },
    {
        "year": "1895",
        "content": "林语堂，中国文学家（1976年逝世）",
        "type": "birth"
    },
    {
        "year": "1896",
        "content": "罗曼·雅各布森，俄罗斯语言学家、文学理论家（1982年逝世）",
        "type": "birth"
    },
    {
        "year": "1900",
        "content": "海伦·海丝，美国女演员（1993年逝世）",
        "type": "birth"
    },
    {
        "year": "1907",
        "content": "冯铿，中国作家，左联五烈士之一（1931年逝世）",
        "type": "birth"
    },
    {
        "year": "1908",
        "content": "俞大酉，中国记者、教育家（1966年逝世）",
        "type": "birth"
    },
    {
        "year": "1909",
        "content": "张文环，台湾小说家（1978年逝世）",
        "type": "birth"
    },
    {
        "year": "1912",
        "content": "托马斯·哈维，美国病理学家（2007年逝世）",
        "type": "birth"
    },
    {
        "year": "1914",
        "content": "龚澎，中国女性外交家（1970年逝世）",
        "type": "birth"
    },
    {
        "year": "1927",
        "content": "陈桥，香港摄影记者（2024年逝世）",
        "type": "birth"
    },
    {
        "year": "1930",
        "content": "野坂昭如，日本作家、歌手、作词家、政治人物（2015年逝世）",
        "type": "birth"
    },
    {
        "year": "1930",
        "content": "李庆忠，中国石油工程专家（2022年逝世）",
        "type": "birth"
    },
    {
        "year": "1932",
        "content": "李来柱，中国人民解放军上将（2023年逝世）",
        "type": "birth"
    },
    {
        "year": "1933",
        "content": "陈炳楠，艺名脱线，台湾男艺人（2022年逝世）",
        "type": "birth"
    },
    {
        "year": "1935",
        "content": "洪流，台湾男演员（2021年逝世）",
        "type": "birth"
    },
    {
        "year": "1936",
        "content": "格哈德·埃特尔，德国化学家",
        "type": "birth"
    },
    {
        "year": "1942",
        "content": "朱国瑞，台湾物理学家",
        "type": "birth"
    },
    {
        "year": "1943",
        "content": "许淇安，香港警务处处长（2009年逝世）",
        "type": "birth"
    },
    {
        "year": "1946",
        "content": "菅直人，日本政治人物，第94任内阁总理大臣",
        "type": "birth"
    },
    {
        "year": "1949",
        "content": "上官灵凤，香港女演员",
        "type": "birth"
    },
    {
        "year": "1949",
        "content": "黄淑仪，香港女演员、主持人",
        "type": "birth"
    },
    {
        "year": "1950",
        "content": "蔡素玉，香港政界人物",
        "type": "birth"
    },
    {
        "year": "1951",
        "content": "苏杏璇，香港甘草演员（2013年逝世）",
        "type": "birth"
    },
    {
        "year": "1951",
        "content": "林保全，香港男性配音员（2015年逝世）",
        "type": "birth"
    },
    {
        "year": "1952",
        "content": "耶西·津巴，不丹政治人物，第4任不丹首相",
        "type": "birth"
    },
    {
        "year": "1954",
        "content": "瑞卡，印度女演员",
        "type": "birth"
    },
    {
        "year": "1955",
        "content": "谢志峰，香港传媒人",
        "type": "birth"
    },
    {
        "year": "1955",
        "content": "邵国华，香港资深电台节目主持（2022年逝世）",
        "type": "birth"
    },
    {
        "year": "1957",
        "content": "高桥留美子，日本漫画家",
        "type": "birth"
    },
    {
        "year": "1962",
        "content": "庹宗华，台湾男演员",
        "type": "birth"
    },
    {
        "year": "1962",
        "content": "阿推，台湾漫画家",
        "type": "birth"
    },
    {
        "year": "1963",
        "content": "梅艳芳，香港女歌手、演员（2003年逝世）",
        "type": "birth"
    },
    {
        "year": "1964",
        "content": "提姆·米勒，美国动画师、导演、视觉特效总监",
        "type": "birth"
    },
    {
        "year": "1965",
        "content": "Toshi，日本男歌手",
        "type": "birth"
    },
    {
        "year": "1966",
        "content": "罗慧娟，香港女演员（2012年逝世）",
        "type": "birth"
    },
    {
        "year": "1966",
        "content": "翟志刚，中国太空人",
        "type": "birth"
    },
    {
        "year": "1966",
        "content": "白灵 ，华裔美国女演员",
        "type": "birth"
    },
    {
        "year": "1966",
        "content": "卡罗琳·贝尔托西 ，美国化学家，2022年诺贝尔化学奖得主",
        "type": "birth"
    },
    {
        "year": "1967",
        "content": "麦可·吉亚奇诺，美国作曲家、导演",
        "type": "birth"
    },
    {
        "year": "1967",
        "content": "葛文·纽森，美国政治人物，现任加州州长",
        "type": "birth"
    },
    {
        "year": "1971",
        "content": "荻野晴朗，日本男性声优",
        "type": "birth"
    },
    {
        "year": "1972",
        "content": "高村和宏，日本动画导演",
        "type": "birth"
    },
    {
        "year": "1973",
        "content": "黄婕菲，台湾女演员",
        "type": "birth"
    },
    {
        "year": "1973",
        "content": "林楚茵，台湾政治人物",
        "type": "birth"
    },
    {
        "year": "1974",
        "content": "颜正国，台湾男演员",
        "type": "birth"
    },
    {
        "year": "1974",
        "content": "蒋子轩，香港画家、填词人、编剧",
        "type": "birth"
    },
    {
        "year": "1975",
        "content": "李佳明，中国中央电视台主持人",
        "type": "birth"
    },
    {
        "year": "1975",
        "content": "江国庆，台湾义务役军人（1997年逝世）",
        "type": "birth"
    },
    {
        "year": "1976",
        "content": "陈宏玮，台湾男性配音员（2010年逝世）",
        "type": "birth"
    },
    {
        "year": "1977",
        "content": "刘芳菲，中国中央电视台主持人",
        "type": "birth"
    },
    {
        "year": "1977",
        "content": "诺瓦·维迪安托，印尼男子羽毛球运动员",
        "type": "birth"
    },
    {
        "year": "1978",
        "content": "刘致妤，台湾女演员",
        "type": "birth"
    },
    {
        "year": "1978",
        "content": "真理翰，韩国男演员",
        "type": "birth"
    },
    {
        "year": "1979",
        "content": "吴尊，汶莱男演员",
        "type": "birth"
    },
    {
        "year": "1979",
        "content": "安七炫，韩国男歌手",
        "type": "birth"
    },
    {
        "year": "1980",
        "content": "熊黛林，中国女模特儿",
        "type": "birth"
    },
    {
        "year": "1981",
        "content": "谭凯琪，香港女艺员",
        "type": "birth"
    },
    {
        "year": "1982",
        "content": "魏如萱，台湾女歌手",
        "type": "birth"
    },
    {
        "year": "1982",
        "content": "丹·史蒂文斯，英国男演员、制片人",
        "type": "birth"
    },
    {
        "year": "1982",
        "content": "亚希尔·卡塔尼，沙特阿拉伯足球运动员",
        "type": "birth"
    },
    {
        "year": "1983",
        "content": "曲婉婷，中国女歌手",
        "type": "birth"
    },
    {
        "year": "1984",
        "content": "郑融，香港女歌手",
        "type": "birth"
    },
    {
        "year": "1984",
        "content": "栗山千明，日本女演员",
        "type": "birth"
    },
    {
        "year": "1984",
        "content": "帕维尔·杜洛夫，俄罗斯程式员、亿万富翁，Telegram创始人",
        "type": "birth"
    },
    {
        "year": "1985",
        "content": "张佑方，台湾女歌手、演员",
        "type": "birth"
    },
    {
        "year": "1985",
        "content": "许钧钧，台湾女演员",
        "type": "birth"
    },
    {
        "year": "1985",
        "content": "崔有华，韩国女演员",
        "type": "birth"
    },
    {
        "year": "1986",
        "content": "谢其均，台湾男演员",
        "type": "birth"
    },
    {
        "year": "1987",
        "content": "廖文扬，台湾棒球选手",
        "type": "birth"
    },
    {
        "year": "1988",
        "content": "郭源元，台湾女演员",
        "type": "birth"
    },
    {
        "year": "1990",
        "content": "邱宇辰，台湾男歌手",
        "type": "birth"
    },
    {
        "year": "1991",
        "content": "张宝儿，香港女艺人",
        "type": "birth"
    },
    {
        "year": "1991",
        "content": "金瑟琪，韩国女演员",
        "type": "birth"
    },
    {
        "year": "1992",
        "content": "藤本树，日本漫画家，代表作《炎拳》、《链锯人》",
        "type": "birth"
    },
    {
        "year": "1992",
        "content": "盖艾琳，英国女歌手",
        "type": "birth"
    },
    {
        "year": "1993",
        "content": "谢震廷，台湾男歌手",
        "type": "birth"
    },
    {
        "year": "1993",
        "content": "马特·伯杰，加拿大男子滑板运动员",
        "type": "birth"
    },
    {
        "year": "1994",
        "content": "裴秀智，韩国女子偶像团体miss A成员",
        "type": "birth"
    },
    {
        "year": "1994",
        "content": "丹羽孝希，日本男子乒乓球运动员",
        "type": "birth"
    },
    {
        "year": "1994",
        "content": "许清雅，中国女演员",
        "type": "birth"
    },
    {
        "year": "1995",
        "content": "大冢纱英，日本女性声优",
        "type": "birth"
    },
    {
        "year": "1995",
        "content": "吴承姬，韩国女子偶像团体CLC成员",
        "type": "birth"
    },
    {
        "year": "1995",
        "content": "艾伦·佩雷斯，澳大利亚职业网球运动员",
        "type": "birth"
    },
    {
        "year": "1996",
        "content": "容启航，新加坡男演员",
        "type": "birth"
    },
    {
        "year": "1997",
        "content": "刘昊然，中国男演员",
        "type": "birth"
    },
    {
        "year": "1999",
        "content": "李恩泉，韩国女演员",
        "type": "birth"
    },
    {
        "year": "2000",
        "content": "刘扬扬，韩国男子偶像团体NCT成员",
        "type": "birth"
    },
    {
        "year": "2000",
        "content": "费利克斯·恩梅查，德国职业足球运动员",
        "type": "birth"
    },
    {
        "year": "2001",
        "content": "刘康，香港政治人物",
        "type": "birth"
    },
    {
        "year": "2002",
        "content": "乔许·吉迪，澳大利亚职业篮球运动员",
        "type": "birth"
    },
    {
        "year": "1581",
        "content": "勃印曩，缅甸东吁王朝国王（1516年出生）",
        "type": "death"
    },
    {
        "year": "1659",
        "content": "阿贝尔·塔斯曼，荷兰探险家、商人（1603年出生）",
        "type": "death"
    },
    {
        "year": "1817",
        "content": "邱良功，清朝武官官员，官至浙江水陆提督（1769年出生）",
        "type": "death"
    },
    {
        "year": "1837",
        "content": "夏尔·傅立叶，法国思想家（1772年出生）",
        "type": "death"
    },
    {
        "year": "1841",
        "content": "谢朝恩，清镇海总兵（出生年不详）",
        "type": "death"
    },
    {
        "year": "1841",
        "content": "裕谦，清朝两江总督（1793年出生）",
        "type": "death"
    },
    {
        "year": "1872",
        "content": "威廉·亨利·西华德，美国律师、地产经纪人、政治家，曾任美国国务卿、美国参议员和纽约州州长（1801年出生）",
        "type": "death"
    },
    {
        "year": "1877",
        "content": "手冢良仙（日语：手冢良仙），幕府末年的医师，漫画家手冢治虫的曾祖父。手冢治虫漫画《向阳之树》即以其为主角（1826年出生）",
        "type": "death"
    },
    {
        "year": "1907",
        "content": "夏尔·当克拉，法国小提琴家、作曲家、教师（1817年出生）",
        "type": "death"
    },
    {
        "year": "1913",
        "content": "桂太郎，日本军人、政治人物，第11、13、15任内阁总理大臣（1848年出生）",
        "type": "death"
    },
    {
        "year": "1941",
        "content": "姉齿松平，日本法官、法学家、律师（1885年出生）",
        "type": "death"
    },
    {
        "year": "1965",
        "content": "冈崎胜男，日本政治人物，前内阁官房长官、外务大臣（1897年出生）",
        "type": "death"
    },
    {
        "year": "1971",
        "content": "权泰夏，韩国男子田径运动员（1906年出生）",
        "type": "death"
    },
    {
        "year": "1973",
        "content": "路德维希·冯·米塞斯，奥地利裔美国经济学家（1881年出生）",
        "type": "death"
    },
    {
        "year": "1974",
        "content": "柳德米拉·帕夫利琴科，苏联女狙击手，有「狙击女王」与「死亡之女」的外号（1916年出生）",
        "type": "death"
    },
    {
        "year": "1983",
        "content": "库尔特·海因里希·德布斯，德国裔美国航空太空工程师（1908年出生）",
        "type": "death"
    },
    {
        "year": "1988",
        "content": "胡安·普约尔·加西亚，西班牙间谍（1912年出生）",
        "type": "death"
    },
    {
        "year": "1980",
        "content": "赵丹，中国电影演员（1915年出生）",
        "type": "death"
    },
    {
        "year": "2000",
        "content": "西丽玛沃·班达拉奈克，斯里兰卡政治人物，前任斯里兰卡总理（1916年出生）",
        "type": "death"
    },
    {
        "year": "2003",
        "content": "埃拉·希尔图宁，芬兰雕塑家&#91;1&#93;。（1922年出生）",
        "type": "death"
    },
    {
        "year": "2004",
        "content": "克里斯托弗·里夫，美国男演员（1952年出生）",
        "type": "death"
    },
    {
        "year": "2005",
        "content": "米尔顿·奥博特，乌干达政治人物，第2任乌干达总统（1924年出生）",
        "type": "death"
    },
    {
        "year": "2013",
        "content": "史考特·卡本特，美国太空人，水星计划七人之一&#91;2&#93;（1925年出生）",
        "type": "death"
    },
    {
        "year": "2016",
        "content": "田中一成，日本男性声优（1967年出生）",
        "type": "death"
    },
    {
        "year": "2021",
        "content": "雅各布·E·古德曼，美国几何学家（1933年出生）",
        "type": "death"
    },
    {
        "year": "2021",
        "content": "阿卜杜勒·卡迪尔·汗，巴基斯坦核技术及冶金工程领域专家，被称为巴基斯坦「核弹之父」（1936年出生）",
        "type": "death"
    },
    {
        "year": "2022",
        "content": "塞尔吉奥·布里根蒂，义大利职业足球运动员（1932年出生）",
        "type": "death"
    },
    {
        "year": "2022",
        "content": "穆拉亚姆·辛格·亚达夫，印度政治人物（1939年出生）",
        "type": "death"
    },
    {
        "year": "2022",
        "content": "曾永义，台湾戏曲、俗文学、诗歌、民俗艺术学者（1941年出生）",
        "type": "death"
    }
]