[
    {
        "year": "238",
        "content": "罗马帝国总督戈尔迪安一世自立为皇帝，并任命戈尔迪安二世为共治皇帝。",
        "type": "event"
    },
    {
        "year": "1312",
        "content": "在法国国王腓力四世施压下，教宗克莱孟五世在维埃纳公会议解散圣殿骑士团。",
        "type": "event"
    },
    {
        "year": "1421",
        "content": "英法百年战争期间的博热战役中，英国人被法国人的苏格兰盟友击败，英国国王亨利五世的兄弟，兰开斯特的托马斯，第一任克拉伦斯公爵（英语：Thomas of Lancaster, 1st Duke of Clarence）战死。",
        "type": "event"
    },
    {
        "year": "1499",
        "content": "士瓦本战争中，在巴塞尔附近发生了布鲁德霍尔茨战役（英语：Battle of Bruderholz）。士瓦本同盟在对阵旧瑞士联邦的战斗中遭遇惨败。",
        "type": "event"
    },
    {
        "year": "1638",
        "content": "安妮·哈钦森因参与唯信仰论之争（英语：Antinomian Controversy）而被麻萨诸塞湾殖民地驱逐。",
        "type": "event"
    },
    {
        "year": "1849",
        "content": "约瑟夫·拉德茨基率领的奥地利帝国军队在诺瓦拉战役中击败萨丁尼亚王国军队。",
        "type": "event"
    },
    {
        "year": "1888",
        "content": "英国英格兰足球总会正式创立英格兰足球联赛，为世界上第一个职业足球联赛。",
        "type": "event"
    },
    {
        "year": "1895",
        "content": "法国导演卢米埃尔兄弟拍摄的作品《工厂大门》在巴黎举办首次电影放映会。",
        "type": "event"
    },
    {
        "year": "1896",
        "content": "卡里劳斯·瓦西拉科斯在为首届夏季奥运做准备的过程中赢得第一场现代马拉松冠军。",
        "type": "event"
    },
    {
        "year": "1913",
        "content": "自封为越南皇帝的潘赤龙遭到法属印度支那殖民政府的逮捕，但隔天支持者开始展开大规模的反抗行动。",
        "type": "event"
    },
    {
        "year": "1913",
        "content": "日本高山测量师野吕宁率领约300人的队伍探勘合欢山，因错估天气发生重大山难，造成至少89人死亡。",
        "type": "event"
    },
    {
        "year": "1914",
        "content": "上海图画美术学院开始使用人体模特儿。",
        "type": "event"
    },
    {
        "year": "1916",
        "content": "中华帝国皇帝袁世凯宣布取消帝制，复任中华民国大总统。",
        "type": "event"
    },
    {
        "year": "1933",
        "content": "纳粹德国于慕尼黑建成为了实施犹太人大屠杀的达豪集中营。",
        "type": "event"
    },
    {
        "year": "1935",
        "content": "波斯王国巴勒维王朝国王礼萨汗正式颁布决定，将国家的名称由波斯更改为伊朗。",
        "type": "event"
    },
    {
        "year": "1938",
        "content": "三星集团前任集团会长李秉喆于韩国大邱成立了三星商会。（三星商会以演变为现今的三星集团）",
        "type": "event"
    },
    {
        "year": "1941",
        "content": "中国国民政府设立上饶集中营。",
        "type": "event"
    },
    {
        "year": "1945",
        "content": "埃及、伊拉克、外约旦等七个阿拉伯国家代表在开罗成立阿拉伯国家联盟。",
        "type": "event"
    },
    {
        "year": "1956",
        "content": "民权领袖马丁·路德·金因抵制种族隔离制度而被判有罪。",
        "type": "event"
    },
    {
        "year": "1963",
        "content": "披头士乐团所录制的第一张专辑《请取悦我》正式发售。",
        "type": "event"
    },
    {
        "year": "1971",
        "content": "轰动香港的「毒马案」开审。",
        "type": "event"
    },
    {
        "year": "1972",
        "content": "美国参议院通过《平等权利修正案》（简称《平权法案》）。",
        "type": "event"
    },
    {
        "year": "1990",
        "content": "美国雅芳公司首次将传销引入中国大陆市场。",
        "type": "event"
    },
    {
        "year": "1990",
        "content": "中华人民共和国与纳米比亚建交。",
        "type": "event"
    },
    {
        "year": "1990",
        "content": "在台北发生、被称为「野百合学运」的三月学运和平结束。",
        "type": "event"
    },
    {
        "year": "1991",
        "content": "《与狼共舞》获第63届奥斯卡最佳影片奖。",
        "type": "event"
    },
    {
        "year": "1992",
        "content": "全美航空405号班机自纽约拉瓜地亚机场起飞后不久于法拉盛湾（英语：Flushing Bay, New York）坠毁，机上51人中27人罹难。此次事故促使研究人员更深入研究冰对航空器的影响。",
        "type": "event"
    },
    {
        "year": "1993",
        "content": "南韩政府公布新经济百日计划。",
        "type": "event"
    },
    {
        "year": "1993",
        "content": "美国英特尔公司制造的新一代微处理器Pentium开始正式出货。",
        "type": "event"
    },
    {
        "year": "1995",
        "content": "俄罗斯太空人瓦列里·波利亚科夫从和平号太空站返回地球，创下单次停留时间最长的纪录。",
        "type": "event"
    },
    {
        "year": "2004",
        "content": "巴勒斯坦哈玛斯创始人艾哈迈德·雅辛在加萨走廊遭到以色列国防军空袭身亡。",
        "type": "event"
    },
    {
        "year": "2007",
        "content": "周俊勋在第11届LG杯世界棋王赛三战两胜第三局半目胜胡耀宇获得个人第一个世界冠军。",
        "type": "event"
    },
    {
        "year": "2008",
        "content": "中国国民党的马英九、萧万长以58%的得票率当选第十二任中华民国正副总统。",
        "type": "event"
    },
    {
        "year": "2018",
        "content": "美国总统唐纳·川普于2018年3月22日签署备忘录，指示美国贸易代表对从中华人民共和国进口的商品征收关税，涉及的商品总计达600亿美元。中华人民共和国商务部其后向128种美国进口商品征税，其中包括美国对中华人民共和国出口最多的货品大豆。2018年中美贸易战于2018年7月6日美东时间凌晨零时一分，北京时间中午十二时一分，正式开战",
        "type": "event"
    },
    {
        "year": "2019",
        "content": "非洲西部国家迦纳首都阿克拉发生两辆巴士对撞，至少60人身亡，另外有28人受伤。",
        "type": "event"
    },
    {
        "year": "2024",
        "content": "伊斯兰国恐怖分子向俄罗斯莫斯科州克拉斯诺戈尔斯克的番红花城市大厅发动恐怖袭击，造成至少144人死亡、551人受伤。",
        "type": "event"
    },
    {
        "year": "1212",
        "content": "后堀河天皇，日本第86代天皇（1234年逝世）",
        "type": "birth"
    },
    {
        "year": "1459",
        "content": "马西米连一世，神圣罗马帝国皇帝（1519年逝世）",
        "type": "birth"
    },
    {
        "year": "1797",
        "content": "威廉一世，德意志帝国皇帝（1888年逝世)",
        "type": "birth"
    },
    {
        "year": "1799",
        "content": "弗里德里希·阿格兰德，普鲁士天文学家（1875年逝世）",
        "type": "birth"
    },
    {
        "year": "1816",
        "content": "约翰·弗雷德里克·肯塞特，美国风景画家、雕刻家（1872年逝世）",
        "type": "birth"
    },
    {
        "year": "1868",
        "content": "罗伯特·密立根，美国物理学家，1923年诺贝尔物理学奖得主（1953年逝世）",
        "type": "birth"
    },
    {
        "year": "1896",
        "content": "贺龙，中国政治家、军事家（1969年逝世）",
        "type": "birth"
    },
    {
        "year": "1909",
        "content": "纳森·罗森，美籍以色列裔物理学家（1995年逝世）",
        "type": "birth"
    },
    {
        "year": "1913",
        "content": "萨比哈·格克琴，土耳其飞行员，世界上第一位女性战斗机飞行员（2001年逝世）",
        "type": "birth"
    },
    {
        "year": "1929",
        "content": "比·南利，马来西亚巨星（1973年逝世）",
        "type": "birth"
    },
    {
        "year": "1929",
        "content": "草间弥生，日本女性前卫艺术家",
        "type": "birth"
    },
    {
        "year": "1930",
        "content": "史蒂芬·桑坦，美国音乐剧、电影音乐作曲家、剧作家（2021年逝世）",
        "type": "birth"
    },
    {
        "year": "1930",
        "content": "帕特·罗伯逊，美国传媒大亨、牧师（2023年逝世）",
        "type": "birth"
    },
    {
        "year": "1931",
        "content": "威廉·夏特纳，美国电影演员",
        "type": "birth"
    },
    {
        "year": "1933",
        "content": "阿布-哈桑·巴尼萨德尔，伊朗政治人物，首任伊朗总统（2021年逝世）",
        "type": "birth"
    },
    {
        "year": "1934",
        "content": "奥林·哈奇，美国政治人物，曾任联邦参议员（2022年逝世）",
        "type": "birth"
    },
    {
        "year": "1940",
        "content": "吴汉润，柬埔寨裔美国医生、演员、作家（1996年逝世）",
        "type": "birth"
    },
    {
        "year": "1941",
        "content": "布鲁诺·冈茨，瑞士电影演员（2019年逝世）",
        "type": "birth"
    },
    {
        "year": "1946",
        "content": "黄家达，香港演员",
        "type": "birth"
    },
    {
        "year": "1948",
        "content": "安德鲁·韦伯，英国剧作家",
        "type": "birth"
    },
    {
        "year": "1951",
        "content": "扎勒米·哈利勒扎德，美国外交官",
        "type": "birth"
    },
    {
        "year": "1953",
        "content": "水树和佳子，日本漫画家，后24年组之一",
        "type": "birth"
    },
    {
        "year": "1957",
        "content": "迈克尔·J·莫斯利，英国制片人（2024年逝世）",
        "type": "birth"
    },
    {
        "year": "1958",
        "content": "法提赫·比罗尔，土耳其经济学家、能源专家",
        "type": "birth"
    },
    {
        "year": "1962",
        "content": "北野勇作，日本科幻小说家、演员",
        "type": "birth"
    },
    {
        "year": "1963",
        "content": "马丁·比斯卡拉，秘鲁政治人物，前任秘鲁总统",
        "type": "birth"
    },
    {
        "year": "1964",
        "content": "朴重勋，韩国男演员",
        "type": "birth"
    },
    {
        "year": "1969",
        "content": "冯友薇，台湾女性配音员",
        "type": "birth"
    },
    {
        "year": "1972",
        "content": "埃尔维斯·斯托克，加拿大花式滑冰运动员",
        "type": "birth"
    },
    {
        "year": "1973",
        "content": "亚历克斯·帕迪利亚，美国政治人物，现任加州联邦参议员",
        "type": "birth"
    },
    {
        "year": "1976",
        "content": "余秀华，中国诗人",
        "type": "birth"
    },
    {
        "year": "1976",
        "content": "高龙伟，台湾棒球选手",
        "type": "birth"
    },
    {
        "year": "1976",
        "content": "丽丝·韦花丝潘，美国女演员",
        "type": "birth"
    },
    {
        "year": "1980",
        "content": "米歇尔·博索纳罗，巴西第一夫人",
        "type": "birth"
    },
    {
        "year": "1981",
        "content": "庄凯勋，台湾男演员",
        "type": "birth"
    },
    {
        "year": "1981",
        "content": "黄镫辉，台湾男演员",
        "type": "birth"
    },
    {
        "year": "1981",
        "content": "Jenya，俄罗斯裔日本女性声优、歌手",
        "type": "birth"
    },
    {
        "year": "1982",
        "content": "萩原舞，日本AV女优",
        "type": "birth"
    },
    {
        "year": "1982",
        "content": "吴恬敏，美国华裔女演员",
        "type": "birth"
    },
    {
        "year": "1985",
        "content": "王丽坤，中国女演员",
        "type": "birth"
    },
    {
        "year": "1985",
        "content": "张峻宁，中国男演员",
        "type": "birth"
    },
    {
        "year": "1986",
        "content": "刘荷娜，韩国女演员",
        "type": "birth"
    },
    {
        "year": "1986",
        "content": "全宝蓝，韩国女子偶像团体T-ara前成员",
        "type": "birth"
    },
    {
        "year": "1987",
        "content": "GAI，中国男饶舌歌手",
        "type": "birth"
    },
    {
        "year": "1989",
        "content": "陈静，香港艺人、模特儿",
        "type": "birth"
    },
    {
        "year": "1989",
        "content": "黄雅莉，中国女歌手、演员",
        "type": "birth"
    },
    {
        "year": "1994",
        "content": "河成云，韩国男子团体前Wanna One成员，现为个人solo",
        "type": "birth"
    },
    {
        "year": "1995",
        "content": "戴祖仪，香港女艺人，歌手",
        "type": "birth"
    },
    {
        "year": "1995",
        "content": "蒋龙，中国男演员",
        "type": "birth"
    },
    {
        "year": "1996",
        "content": "布桑兰·恩布鲁庞，泰国女子羽球运动员",
        "type": "birth"
    },
    {
        "year": "1997",
        "content": "佐藤元，日本男性声优",
        "type": "birth"
    },
    {
        "year": "1997",
        "content": "路易斯·菲利佩，义大利职业足球运动员",
        "type": "birth"
    },
    {
        "year": "1998",
        "content": "川后阳菜，日本女子偶像团体乃木坂46成员",
        "type": "birth"
    },
    {
        "year": "2000",
        "content": "欧帕瓦·吉沙晚迪，泰国男演员",
        "type": "birth"
    },
    {
        "year": "2001",
        "content": "咸元进，韩国男子偶像团体CRAVITY成员",
        "type": "birth"
    },
    {
        "year": "生不详",
        "content": "尾崎真实，日本女性声优",
        "type": "birth"
    },
    {
        "year": "1393",
        "content": "蓝玉，明朝大将（生年不详）",
        "type": "death"
    },
    {
        "year": "1687",
        "content": "让-巴普蒂斯特·吕利，义大利裔法国巴洛克作曲家（1632年出生）",
        "type": "death"
    },
    {
        "year": "1727",
        "content": "穆莱·伊斯梅尔，摩洛哥苏丹（1645年出生）",
        "type": "death"
    },
    {
        "year": "1832",
        "content": "约翰·沃尔夫冈·冯·歌德，德国诗人（1749年出生）",
        "type": "death"
    },
    {
        "year": "1853",
        "content": "让-图桑·阿里吉·德·卡萨诺瓦，法国外交官、军人（1778年出生）",
        "type": "death"
    },
    {
        "year": "1913",
        "content": "宋教仁，中国近代民主革命家（1882年出生）",
        "type": "death"
    },
    {
        "year": "1916",
        "content": "克里斯蒂安·格里彭克尔，德国画家（1839年出生）",
        "type": "death"
    },
    {
        "year": "1943",
        "content": "新美南吉，日本儿童文学作家（1913年出生）",
        "type": "death"
    },
    {
        "year": "1969",
        "content": "恩斯特·德意志，德国演员（1890年出生）",
        "type": "death"
    },
    {
        "year": "1971",
        "content": "万荣华，英国长老教会传教士，台湾足球运动先驱（1886年出生）",
        "type": "death"
    },
    {
        "year": "1977",
        "content": "谭富英，中国著名京剧演员（1906年出生）",
        "type": "death"
    },
    {
        "year": "1995",
        "content": "黄汲清，中国地质学家（1904年出生）",
        "type": "death"
    },
    {
        "year": "2001",
        "content": "威廉·汉纳，美国动画师、导演、制片人、配音演员、卡通画师（1910年出生）",
        "type": "death"
    },
    {
        "year": "2001",
        "content": "萨比哈·格克琴，土耳其飞行员，世界上第一位女性战斗机飞行员（1913年出生）",
        "type": "death"
    },
    {
        "year": "2004",
        "content": "潘霞，中国电视剧女导演（1937年出生）",
        "type": "death"
    },
    {
        "year": "2004",
        "content": "艾哈迈德·亚辛，巴勒斯坦伊斯兰抵抗运动哈马斯的精神领袖与创始人（1937年出生）",
        "type": "death"
    },
    {
        "year": "2005",
        "content": "丹下健三，日本建筑师（1913年出生）",
        "type": "death"
    },
    {
        "year": "2007",
        "content": "村上弘，日本政治人物（1921年出生）",
        "type": "death"
    },
    {
        "year": "2008",
        "content": "弗朗茨·斯蒂格勒，德国飞行员（1915年出生）",
        "type": "death"
    },
    {
        "year": "2010",
        "content": "樊畿，华裔美国数学家（1914年出生）",
        "type": "death"
    },
    {
        "year": "2010",
        "content": "詹姆士·W·布拉克，苏格兰药理学家，1988年诺贝尔生理学或医学奖得主（1924年出生）",
        "type": "death"
    },
    {
        "year": "2016",
        "content": "罗柏特·福特，加拿大政治人物、商人（1969年出生）",
        "type": "death"
    },
    {
        "year": "2020",
        "content": "梁天，香港演员、电视剧编导及监制（1932年出生）",
        "type": "death"
    },
    {
        "year": "2020",
        "content": "刘真，台湾艺人、舞蹈家（1975年出生）",
        "type": "death"
    },
    {
        "year": "2023",
        "content": "团时朗，日本男演员（1949年出生）",
        "type": "death"
    },
    {
        "year": "2023",
        "content": "吴永培，台湾稻米培育专家（1965年出生）",
        "type": "death"
    }
]