[
    {
        "year": "1008",
        "content": "宋真宗封禅泰山。",
        "type": "event"
    },
    {
        "year": "1174",
        "content": "埃及阿尤布王朝苏丹萨拉丁征服大马士革。",
        "type": "event"
    },
    {
        "year": "1644",
        "content": "英国诗人约翰·密尔顿因反对内战时期的审查制度，而发表提倡言论自由的《论出版自由》。",
        "type": "event"
    },
    {
        "year": "1920",
        "content": "陈独秀主持起草《中国共产党宣言》。",
        "type": "event"
    },
    {
        "year": "1924",
        "content": "美国天文学家爱德温·哈伯指出仙女座星系并不属于银河系，同时宇宙亦存在众多星系。",
        "type": "event"
    },
    {
        "year": "1925",
        "content": "国民党右派召开西山会议，排斥共产党人。",
        "type": "event"
    },
    {
        "year": "1925",
        "content": "国民革命军北伐军的一支机械化部队叶挺独立团成立。",
        "type": "event"
    },
    {
        "year": "1936",
        "content": "七君子事件：沈钧儒、章乃器等七人被国民党当局逮捕。",
        "type": "event"
    },
    {
        "year": "1940",
        "content": "第二次世界大战：罗马尼亚王国签署三国同盟条约加入轴心国。",
        "type": "event"
    },
    {
        "year": "1943",
        "content": "中华民国蒋中正、美国罗斯福、英国邱吉尔在埃及召开开罗会议。",
        "type": "event"
    },
    {
        "year": "1944",
        "content": "自由法国将领菲利普·勒克莱尔领导的法军，成功在击败德军后解放了法国东部重镇史特拉斯堡。",
        "type": "event"
    },
    {
        "year": "1949",
        "content": "中华人民共和国与阿尔巴尼亚人民共和国建立外交关系。",
        "type": "event"
    },
    {
        "year": "1949",
        "content": "中共中央西南局于湖南常德市成立。",
        "type": "event"
    },
    {
        "year": "1957",
        "content": "来自64个国家的共产党代表签订《和平宣言》，要求停止军备竞赛与核武器试验。",
        "type": "event"
    },
    {
        "year": "1959",
        "content": "法国总统戴高乐于斯特拉斯堡的演讲中呼吁欧洲各国开始实行一体化。",
        "type": "event"
    },
    {
        "year": "1963",
        "content": "英国广播公司科幻电视剧《神秘博士》首次播出。",
        "type": "event"
    },
    {
        "year": "1969",
        "content": "甘地夫人取得印度国大党的控制权。",
        "type": "event"
    },
    {
        "year": "1970",
        "content": "葡萄牙入侵几内亚。",
        "type": "event"
    },
    {
        "year": "1971",
        "content": "中华人民共和国常驻联合国代表黄华首次代表中国出席联合国安全理事会会议。",
        "type": "event"
    },
    {
        "year": "1972",
        "content": "苏联最后一次N1运载火箭升空实验因发动机失效而告终。",
        "type": "event"
    },
    {
        "year": "1977",
        "content": "阿根廷西部发生强烈地震，50人死亡。",
        "type": "event"
    },
    {
        "year": "1979",
        "content": "香港居民从当日起前往新界边境禁区及米埔自然护理区时需出示身分证。",
        "type": "event"
    },
    {
        "year": "1980",
        "content": "意大利南部发生芮氏规模6.8地震，超过百万人受灾。",
        "type": "event"
    },
    {
        "year": "1983",
        "content": "中共中央总书记胡耀邦对日本进行正式友好访问。成立“中日友好21世纪委员会”。",
        "type": "event"
    },
    {
        "year": "1985",
        "content": "三名阿布·尼达尔恐怖组织成员劫持了埃及航空公司648航班，埃及派出突击队员前往马耳他解救人质，事件造成60人死亡。",
        "type": "event"
    },
    {
        "year": "1987",
        "content": "香港亚洲电视位于九龙塘广播道的总台发生4级大火，节目一度中断广播。",
        "type": "event"
    },
    {
        "year": "1988",
        "content": "香港轻便铁路三小时内发生两宗意外事故。",
        "type": "event"
    },
    {
        "year": "1992",
        "content": "世界上首支手机IBM Simon于美国拉斯维加斯的计算机经销商博览会亮相。",
        "type": "event"
    },
    {
        "year": "1996",
        "content": "安哥拉加入世界贸易组织。",
        "type": "event"
    },
    {
        "year": "1996",
        "content": "遭到劫持的衣索比亚航空961号班机在葛摩附近印度洋海域坠毁，造成125人死亡。",
        "type": "event"
    },
    {
        "year": "2001",
        "content": "香港警方在屯门一艘内河船截获近十年来最大批中国内地非法入境者，为数150多人，这群人蛇来自福建，打算偷渡前往日本。",
        "type": "event"
    },
    {
        "year": "2001",
        "content": "64个国家代表于布达佩斯签署《网路犯罪公约》。",
        "type": "event"
    },
    {
        "year": "2003",
        "content": "香港区议会选举投票率创新高，达44%，亲政府政党民建联大败，反映市民求变及对现况不满。",
        "type": "event"
    },
    {
        "year": "2003",
        "content": "在指控其涉嫌选举舞弊的群众示威压力下，乔治亚总统爱德华·谢瓦尔德纳泽宣布辞职。",
        "type": "event"
    },
    {
        "year": "2008",
        "content": "第20届亚太经济合作组织领导人峰会于秘鲁首都利马举行。",
        "type": "event"
    },
    {
        "year": "2010",
        "content": "南韩延坪岛事件，朝鲜趁著韩国在边境演习以火炮炮轰延坪岛，造成4名韩国军人死亡、19人受伤。",
        "type": "event"
    },
    {
        "year": "2011",
        "content": "经过近一年的反政府示威后，叶门总统阿里·阿布杜拉·沙雷签署协议，同意交出权力。",
        "type": "event"
    },
    {
        "year": "2018",
        "content": "巴基斯坦西北部城镇一个露天市集发生爆炸，至少30人死亡，40人受伤。",
        "type": "event"
    },
    {
        "year": "2021",
        "content": "保加利亚西部佩尔尼克州A3高速公路发生巴士车祸，造成46人死亡。",
        "type": "event"
    },
    {
        "year": "912",
        "content": "奥托一世，东法兰克国王、神圣罗马帝国皇帝（973年逝世）",
        "type": "birth"
    },
    {
        "year": "1221",
        "content": "阿方索十世，卡斯蒂利亚王国国王（1284年逝世）",
        "type": "birth"
    },
    {
        "year": "1616",
        "content": "约翰·沃利斯，英国数学家（1703年逝世）",
        "type": "birth"
    },
    {
        "year": "1632",
        "content": "让·马比雍，法国本笃会僧侣，西方古文献学、古文字学创始人（1707年逝世）",
        "type": "birth"
    },
    {
        "year": "1749",
        "content": "爱德华·拉特利奇，美国南卡罗莱那州州长（1800年逝世）",
        "type": "birth"
    },
    {
        "year": "1760",
        "content": "格拉克斯·巴贝夫，法国大革命时期政治活动者、记者（1797年逝世）",
        "type": "birth"
    },
    {
        "year": "1804",
        "content": "富兰克林·皮尔斯，美国政治人物，第14任美国总统（1869年逝世）",
        "type": "birth"
    },
    {
        "year": "1837",
        "content": "约翰内斯·范德瓦耳斯，荷兰物理学家，1910年诺贝尔物理学奖得主（1923年逝世）",
        "type": "birth"
    },
    {
        "year": "1849",
        "content": "洪天贵福，太平天国第二代君主（1864年逝世）",
        "type": "birth"
    },
    {
        "year": "1859",
        "content": "比利小子，美国著名枪手、西部传奇人物（1881年逝世）",
        "type": "birth"
    },
    {
        "year": "1860",
        "content": "卡尔·布兰廷，瑞典政治家、社会民主运动先驱，1921年诺贝尔和平奖得主（1925年逝世）",
        "type": "birth"
    },
    {
        "year": "1867",
        "content": "英敛之，清末民初教育家、记者（1926年逝世）",
        "type": "birth"
    },
    {
        "year": "1874",
        "content": "西奥多·赖曼，美国物理学家（1954年逝世）",
        "type": "birth"
    },
    {
        "year": "1875",
        "content": "阿纳托利·卢那察尔斯基，俄罗斯马克思主义革命家、艺术批评家、记者（1933年逝世）",
        "type": "birth"
    },
    {
        "year": "1876",
        "content": "曼努埃尔·德·法雅，西班牙古典音乐作曲家（1946年逝世）",
        "type": "birth"
    },
    {
        "year": "1878",
        "content": "欧尼斯特·金，美国海军五星上将（1956年逝世）",
        "type": "birth"
    },
    {
        "year": "1882",
        "content": "约翰·拉贝，德国商人，避难所南京安全区发起人（1950年逝世）",
        "type": "birth"
    },
    {
        "year": "1887",
        "content": "亨利·莫塞莱，英国物理学家，原子序数发现者（1915年逝世）",
        "type": "birth"
    },
    {
        "year": "1887",
        "content": "鲍里斯·卡洛夫，英国男演员，以演出科学怪人闻名（1969年逝世）",
        "type": "birth"
    },
    {
        "year": "1890",
        "content": "埃尔·利西茨基，苏联艺术家、设计师、摄影师、印刷家、辩论家、建筑师（1941年逝世）",
        "type": "birth"
    },
    {
        "year": "1893",
        "content": "许聪敏，台湾实业家、企业家、政治人物、慈善家（1983年逝世）",
        "type": "birth"
    },
    {
        "year": "1896",
        "content": "克莱门特·哥特瓦尔德，捷克斯洛伐克共产党领导人（1953年逝世）",
        "type": "birth"
    },
    {
        "year": "1899",
        "content": "曼努埃尔·马夏多，巴西现代卡波耶拉武术之父（1974年逝世）",
        "type": "birth"
    },
    {
        "year": "1912",
        "content": "马歇尔·霍洛威，美国物理学家（1991年逝世）",
        "type": "birth"
    },
    {
        "year": "1916",
        "content": "麦可·高福，英国电影演员（2011年逝世）",
        "type": "birth"
    },
    {
        "year": "1917",
        "content": "伊莉莎白·斯科特，美国数学家（1988年逝世）",
        "type": "birth"
    },
    {
        "year": "1920",
        "content": "保罗·策兰，法国犹太诗人、翻译家（1970年逝世）",
        "type": "birth"
    },
    {
        "year": "1920",
        "content": "伟恩·第伯，美国普普艺术画家（2021年逝世）",
        "type": "birth"
    },
    {
        "year": "1925",
        "content": "何塞·杜阿尔特，萨尔瓦多总统（1990年逝世）",
        "type": "birth"
    },
    {
        "year": "1925",
        "content": "爱德华·F·摩尔，美国数学家、计算机科学家（2003年逝世）",
        "type": "birth"
    },
    {
        "year": "1926",
        "content": "实谛·赛·巴巴，印度教上师与精神领袖、慈善活动家、教育家（2011年逝世）",
        "type": "birth"
    },
    {
        "year": "1927",
        "content": "安杰洛·索达诺，义大利籍天主教级枢机（2022年逝世）",
        "type": "birth"
    },
    {
        "year": "1928",
        "content": "杰瑞·巴克，美国音乐剧作曲家（2010年逝世）",
        "type": "birth"
    },
    {
        "year": "1928",
        "content": "松永光，日本政治人物（2022年逝世）",
        "type": "birth"
    },
    {
        "year": "1931",
        "content": "谢法新，香港政府官员（2008年逝世）",
        "type": "birth"
    },
    {
        "year": "1932",
        "content": "田中邦卫，日本男演员（2021年逝世）",
        "type": "birth"
    },
    {
        "year": "1933",
        "content": "克里斯托弗·潘德列茨基，波兰当代古典音乐作曲家、指挥家（2020年逝世）",
        "type": "birth"
    },
    {
        "year": "1934",
        "content": "卢·霍德，澳洲男子网球运动员（1994年逝世）",
        "type": "birth"
    },
    {
        "year": "1945",
        "content": "皮埃尔·帕西，刚果共和国政治人物、外交家",
        "type": "birth"
    },
    {
        "year": "1949",
        "content": "维克托·波加诺夫斯基，乌克兰男子马术运动员",
        "type": "birth"
    },
    {
        "year": "1950",
        "content": "查克·舒默，美国政治人物，现任美国参议院多数党领袖",
        "type": "birth"
    },
    {
        "year": "1951",
        "content": "笑福亭鹤瓶，日本演员",
        "type": "birth"
    },
    {
        "year": "1953",
        "content": "约翰·梅杰，荷兰作曲家、编曲家、长号演奏家、指挥家",
        "type": "birth"
    },
    {
        "year": "1954",
        "content": "罗斯·布朗，英国工程师，曾任一级方程式法拉利车队技术总监长达十年",
        "type": "birth"
    },
    {
        "year": "1955",
        "content": "鲁多维科·伊诺第，义大利当代古典主义音乐作曲家、钢琴家",
        "type": "birth"
    },
    {
        "year": "1961",
        "content": "士郎正宗，日本漫画家",
        "type": "birth"
    },
    {
        "year": "1962",
        "content": "尼古拉斯·马杜洛，委内瑞拉政治人物，现任委内瑞拉总统",
        "type": "birth"
    },
    {
        "year": "1963",
        "content": "鹰森淑乃，日本女性声优",
        "type": "birth"
    },
    {
        "year": "1963",
        "content": "西森博之，日本漫画家",
        "type": "birth"
    },
    {
        "year": "1966",
        "content": "凡松·卡塞，法国演员、导演、电影制作人、剧作家和配音员",
        "type": "birth"
    },
    {
        "year": "1967",
        "content": "莎莉·理查德森，美国女演员",
        "type": "birth"
    },
    {
        "year": "1967",
        "content": "威尔·弗林特，美国职业棒球运动员",
        "type": "birth"
    },
    {
        "year": "1968",
        "content": "何嘉丽，香港女子击剑运动员",
        "type": "birth"
    },
    {
        "year": "1969",
        "content": "梁琤，香港演员",
        "type": "birth"
    },
    {
        "year": "1970",
        "content": "戴军，中国歌手、主持人、演员",
        "type": "birth"
    },
    {
        "year": "1970",
        "content": "阮小仪，香港商业电台DJ",
        "type": "birth"
    },
    {
        "year": "1971",
        "content": "维恩·贝克，美国职业篮球运动员",
        "type": "birth"
    },
    {
        "year": "1972",
        "content": "童爱玲，香港演员",
        "type": "birth"
    },
    {
        "year": "1975",
        "content": "施念慈，香港女艺人",
        "type": "birth"
    },
    {
        "year": "1976",
        "content": "梁慧恩，香港主持人",
        "type": "birth"
    },
    {
        "year": "1978",
        "content": "赵骏亚，台湾演员",
        "type": "birth"
    },
    {
        "year": "1979",
        "content": "凯莉·布鲁克，英国模特、女演员、泳装设计师、电视节目主持人",
        "type": "birth"
    },
    {
        "year": "1979",
        "content": "尼哈特·卡赫维奇，土耳其职业足球运动员",
        "type": "birth"
    },
    {
        "year": "1982",
        "content": "阿萨法·鲍威尔，牙买加田径短跑运动员",
        "type": "birth"
    },
    {
        "year": "1982",
        "content": "楠迪·宗拉维蒙，泰国女演员、歌手、模特儿",
        "type": "birth"
    },
    {
        "year": "1984",
        "content": "卢卡斯·格拉贝尔，美国演员",
        "type": "birth"
    },
    {
        "year": "1985",
        "content": "傅小芸，台湾演员",
        "type": "birth"
    },
    {
        "year": "1985",
        "content": "安贤洙，韩裔俄罗斯男子短道速滑运动员",
        "type": "birth"
    },
    {
        "year": "1986",
        "content": "叶丽嘉，香港艺术家、舞台剧演员",
        "type": "birth"
    },
    {
        "year": "1986",
        "content": "田中美奈实，日本女艺人",
        "type": "birth"
    },
    {
        "year": "1988",
        "content": "安妮，台湾女艺人",
        "type": "birth"
    },
    {
        "year": "1988",
        "content": "宫泽艾玛，日本女艺人",
        "type": "birth"
    },
    {
        "year": "1990",
        "content": "玛丽亚·艾莉由里，日本AV女优",
        "type": "birth"
    },
    {
        "year": "1991",
        "content": "山川穗高，日本职业棒球运动员",
        "type": "birth"
    },
    {
        "year": "1991",
        "content": "鲁斯兰·明加索夫，土库曼职业足球员",
        "type": "birth"
    },
    {
        "year": "1992",
        "content": "麦莉·希拉，美国创作歌手、演员",
        "type": "birth"
    },
    {
        "year": "1992",
        "content": "高恩妃，韩国女子偶像团体Ladies' Code成员（2014年逝世）",
        "type": "birth"
    },
    {
        "year": "1993",
        "content": "L.Joe，韩国男子偶像团体TEEN TOP成员",
        "type": "birth"
    },
    {
        "year": "1993",
        "content": "金永彬，韩国男子偶像团体SF9队长",
        "type": "birth"
    },
    {
        "year": "1993",
        "content": "乔欣，中国女演员",
        "type": "birth"
    },
    {
        "year": "1994",
        "content": "张九龄，中国相声演员",
        "type": "birth"
    },
    {
        "year": "1994",
        "content": "何恋慈，马来西亚女艺人",
        "type": "birth"
    },
    {
        "year": "1995",
        "content": "金娜英，韩国女子偶像团体gu9udan成员",
        "type": "birth"
    },
    {
        "year": "1996",
        "content": "詹姆士·麦迪森，英国足球运动员",
        "type": "birth"
    },
    {
        "year": "1997",
        "content": "于之莹，中国围棋职业棋手",
        "type": "birth"
    },
    {
        "year": "1998",
        "content": "宫泽艾玛，日本女艺人",
        "type": "birth"
    },
    {
        "year": "1998",
        "content": "卢知宣，韩国女子偶像团体fromis 9成员",
        "type": "birth"
    },
    {
        "year": "2001",
        "content": "蒂诺·安乔林，英格兰职业足球运动员",
        "type": "birth"
    },
    {
        "year": "386",
        "content": "晋废帝，东晋第七代皇帝（342年出生）",
        "type": "death"
    },
    {
        "year": "615",
        "content": "圣高隆邦，爱尔兰僧侣（540年出生）",
        "type": "death"
    },
    {
        "year": "947",
        "content": "贝特霍尔德，巴伐利亚公爵（900年出生）",
        "type": "death"
    },
    {
        "year": "955",
        "content": "埃德雷德，英格兰国王（923年出生）",
        "type": "death"
    },
    {
        "year": "1407",
        "content": "路易一世，奥尔良公爵（1372年出生）",
        "type": "death"
    },
    {
        "year": "1457",
        "content": "拉斯洛五世，匈牙利国王（1440年出生）",
        "type": "death"
    },
    {
        "year": "1719",
        "content": "延龄君李昍，朝鲜王朝后期王族（1699年出生）",
        "type": "death"
    },
    {
        "year": "1814",
        "content": "埃尔布里奇·格里，美国政治人物、外交官，第5任美国副总统（1744年出生）",
        "type": "death"
    },
    {
        "year": "1826",
        "content": "约翰·波德，德国天文学家（1747年出生）",
        "type": "death"
    },
    {
        "year": "1864",
        "content": "瓦西里·雅可夫列维奇·斯特鲁维，俄国天文学家（1793年出生）",
        "type": "death"
    },
    {
        "year": "1864",
        "content": "洪仁玕，太平天国领袖（1822年出生）",
        "type": "death"
    },
    {
        "year": "1896",
        "content": "樋口一叶，日本女性小说家（1872年出生）",
        "type": "death"
    },
    {
        "year": "1924",
        "content": "卡洛斯·杜兰·卡廷，哥斯大黎加医生、政治人物，第14任哥斯大黎加总统（1852年出生）",
        "type": "death"
    },
    {
        "year": "1943",
        "content": "东嘉生，台湾经济学者（1910年出生）",
        "type": "death"
    },
    {
        "year": "1968",
        "content": "上官云珠，中国话剧女演员、电影演员（1920年出生）",
        "type": "death"
    },
    {
        "year": "1973",
        "content": "早川雪洲，日本男演员（1889年出生）",
        "type": "death"
    },
    {
        "year": "1990",
        "content": "阮文心，越南政治人物，曾任越南国首相（1895年出生）",
        "type": "death"
    },
    {
        "year": "1990",
        "content": "罗尔德·达尔，挪威籍英国儿童文学作家、剧作家、短篇小说作家（1916年出生）",
        "type": "death"
    },
    {
        "year": "2006",
        "content": "亚历山大·利特维年科，前俄罗斯特工，疑遭俄罗斯政府毒死（1962年出生）",
        "type": "death"
    },
    {
        "year": "2006",
        "content": "邹承鲁，中国著名生物化学家（1923年出生）",
        "type": "death"
    },
    {
        "year": "2006",
        "content": "菲利浦·诺瓦雷，法国著名演员（1930年出生）",
        "type": "death"
    },
    {
        "year": "2009",
        "content": "杨宪益，中国翻译家、外国文学研究专家、诗人（1915年出生）",
        "type": "death"
    },
    {
        "year": "2011",
        "content": "杨日松，台湾著名法医，罹大肠癌病逝（1927年出生）",
        "type": "death"
    },
    {
        "year": "2011",
        "content": "黄纬禄，中国导弹技术专家（1916年出生）",
        "type": "death"
    },
    {
        "year": "2017",
        "content": "张阳，中国人民解放军上将，中央军委原委员，中央军委政治工作部原主任，畏罪自缢（1951年出生）",
        "type": "death"
    },
    {
        "year": "2019",
        "content": "流沙河，中国诗人（1931年出生）",
        "type": "death"
    },
    {
        "year": "2019",
        "content": "白德彰，中国导演（1931年出生）",
        "type": "death"
    },
    {
        "year": "2021",
        "content": "全斗焕，大韩民国第11、12任总统（1931年出生）",
        "type": "death"
    },
    {
        "year": "2021",
        "content": "詹姆斯·菲茨-艾伦·米切尔，圣文森政治家，第2任圣文森总理（1931年出生）",
        "type": "death"
    }
]