[
    {
        "year": "258",
        "content": "司马昭率领的曹魏军队攻陷寿春，诸葛诞被杀，叛乱被平定。",
        "type": "event"
    },
    {
        "year": "1356",
        "content": "朱元璋占领南京。",
        "type": "event"
    },
    {
        "year": "1741",
        "content": "普鲁士王国国王腓特烈二世的军队在莫尔维茨会战中击败哈布斯堡君主国军队。",
        "type": "event"
    },
    {
        "year": "1809",
        "content": "拿破仑战争：第五次反法同盟始于奥地利入侵巴伐利亚，巴伐利亚当时是法国的从属国。",
        "type": "event"
    },
    {
        "year": "1815",
        "content": "荷属东印度坦博拉火山发生人类历史上最大规模的爆发，造成9.2万人死亡和全球气候异常。",
        "type": "event"
    },
    {
        "year": "1840",
        "content": "英国议会就对华战争的问题进行辩论。",
        "type": "event"
    },
    {
        "year": "1872",
        "content": "朱利叶斯·斯特林·莫顿于内布拉斯加州创办美国首个及全球首次现代意义上的植树节。",
        "type": "event"
    },
    {
        "year": "1912",
        "content": "英国白星航运皇家邮轮铁达尼号离开南安普敦展开首航，预定目的地为美国纽约。",
        "type": "event"
    },
    {
        "year": "1925",
        "content": "美国作家弗朗西斯·斯科特·菲茨杰拉德的小说《了不起的盖茨比》在纽约出版发行。",
        "type": "event"
    },
    {
        "year": "1930",
        "content": "台湾嘉南大圳通水启用。",
        "type": "event"
    },
    {
        "year": "1946",
        "content": "日本进行战后第一次国会选举。",
        "type": "event"
    },
    {
        "year": "1946",
        "content": "远东国际军事法庭开始在东京审判日本战犯。",
        "type": "event"
    },
    {
        "year": "1946",
        "content": "阿拉伯联盟在开罗举行会议。",
        "type": "event"
    },
    {
        "year": "1956",
        "content": "山东足球历史上第一支专业足球队 - 山东省体育训练班足球队成立。",
        "type": "event"
    },
    {
        "year": "1959",
        "content": "日本皇太子明仁亲王与正田美智子正式结婚，成为第一位迎娶平民的日本皇太子。",
        "type": "event"
    },
    {
        "year": "1963",
        "content": "美国核潜艇长尾鲨号核动力攻击型潜艇在鳕鱼角附近海域沉没，舰上129人全数死亡。",
        "type": "event"
    },
    {
        "year": "1970",
        "content": "英国摇滚音乐家保罗·麦卡尼因为和成员有严重的经济纠纷，宣布退出披头四乐团。",
        "type": "event"
    },
    {
        "year": "1971",
        "content": "美国乒乓球队受到中国的邀请抵达北京访问，乒乓外交开始。",
        "type": "event"
    },
    {
        "year": "1972",
        "content": "美苏签订《禁止生物武器公约》。",
        "type": "event"
    },
    {
        "year": "1985",
        "content": "《中英联合声明》获中华人民共和国第六届全国人民代表大会第三次会议通过批准，同日，会议又通过成立香港基本法起草委员会。",
        "type": "event"
    },
    {
        "year": "1990",
        "content": "香港华懋集团创办人王德辉第二次被绑架，其后失踪，1999年被裁定在法律上「死亡」。",
        "type": "event"
    },
    {
        "year": "1998",
        "content": "爱尔兰和英国在贝尔法斯特签署《贝尔法斯特协议》，推动北爱尔兰的和平进程。",
        "type": "event"
    },
    {
        "year": "2010",
        "content": "波兰总统莱赫·卡钦斯基专机在俄罗斯斯摩伦斯克降落时坠毁，造成机上96人遇难。",
        "type": "event"
    },
    {
        "year": "2011",
        "content": "2011年北京守望教会户外敬拜事件：北京守望家庭教会因政府限制其聚会场所，开始户外敬拜，上百位参加户外敬拜的信徒被警察抓捕，强迫写保证书，放弃户外敬拜。",
        "type": "event"
    },
    {
        "year": "2012",
        "content": "薄熙来王立军事件：中共中央发布对薄熙来的处理决定，司法机关对其妻薄谷开来涉嫌故意杀人案进行复查。",
        "type": "event"
    },
    {
        "year": "2017",
        "content": "港铁东涌线和观塘线先后发生故障，其中观塘线于傍晚下班繁忙时间发生电力故障，列车服务受阻逾两小时，其中一辆列车停留管道近一小时后，车长才打开车头紧急逃生门疏散乘客，至少8人不适送院，港铁需为今次延误事故罚款300万元。",
        "type": "event"
    },
    {
        "year": "2019",
        "content": "事件视界望远镜计划科学家召开记者会，发布人类史上首张直接对黑洞观测的天文影像。",
        "type": "event"
    },
    {
        "year": "2024",
        "content": "中共中央总书记习近平与中华民国前总统、中国国民党前主席马英九在北京人民大会堂举行两人第二次会面。",
        "type": "event"
    },
    {
        "year": "401",
        "content": "狄奥多西二世，东罗马帝国皇帝。（450年逝世）",
        "type": "birth"
    },
    {
        "year": "1480",
        "content": "菲利贝托二世，萨伏依公爵。（1504年逝世）",
        "type": "birth"
    },
    {
        "year": "1583",
        "content": "胡果·格老秀斯，荷兰哲学家。（1645年逝世）",
        "type": "birth"
    },
    {
        "year": "1769",
        "content": "让·拉纳，法国军人、政治人物，法国元帅。（1809年逝世）",
        "type": "birth"
    },
    {
        "year": "1794",
        "content": "马修·培理，美国海军将领，因率领黑船打开锁国时期的日本国门而闻名于世。（1858年逝世）",
        "type": "birth"
    },
    {
        "year": "1827",
        "content": "卢·华莱士，美国联邦军将军、作家。（1905年逝世）",
        "type": "birth"
    },
    {
        "year": "1847",
        "content": "约瑟夫·普利兹，美籍匈牙利报业大亨。（1911年逝世）",
        "type": "birth"
    },
    {
        "year": "1882",
        "content": "弗朗西丝·珀金斯，美国政治家，美国第一位女性内阁。（1965年逝世）",
        "type": "birth"
    },
    {
        "year": "1908",
        "content": "郭雪湖，台湾画家。（2012年逝世）",
        "type": "birth"
    },
    {
        "year": "1913",
        "content": "司徒惠，香港工程师、建筑师。（1991年逝世）",
        "type": "birth"
    },
    {
        "year": "1917",
        "content": "罗伯特·伯恩斯·伍德沃德，美国化学家，1965年诺贝尔化学奖得主。（1979年逝世）",
        "type": "birth"
    },
    {
        "year": "1922",
        "content": "小约瑟夫·霍奇斯，美国统计学家。（2000年逝世）",
        "type": "birth"
    },
    {
        "year": "1927",
        "content": "张厚粲，中国心理学家。（2022年逝世）",
        "type": "birth"
    },
    {
        "year": "1929",
        "content": "麦斯·冯·西度，瑞典裔法国男演员。（2020年逝世）",
        "type": "birth"
    },
    {
        "year": "1932",
        "content": "奥玛·雪瑞夫，埃及演员。（2015年逝世）",
        "type": "birth"
    },
    {
        "year": "1939",
        "content": "水岛新司，日本漫画家。（2022年逝世）",
        "type": "birth"
    },
    {
        "year": "1939",
        "content": "刘洵，香港男演员。",
        "type": "birth"
    },
    {
        "year": "1949",
        "content": "李璇，台湾女演员。",
        "type": "birth"
    },
    {
        "year": "1950",
        "content": "和田现子，韩裔日本女歌手、艺人、主持、演员、企业家。",
        "type": "birth"
    },
    {
        "year": "1951",
        "content": "史蒂芬·席格，美国演员。",
        "type": "birth"
    },
    {
        "year": "1952",
        "content": "格里高利·亚夫林斯基，俄罗斯经济学家、政治人物。",
        "type": "birth"
    },
    {
        "year": "1969",
        "content": "完颜慧德，中国心理咨询师、网路红人。",
        "type": "birth"
    },
    {
        "year": "1970",
        "content": "颜恝，中国女演员。",
        "type": "birth"
    },
    {
        "year": "1972",
        "content": "赵文卓，中国男演员。",
        "type": "birth"
    },
    {
        "year": "1973",
        "content": "吉绕姆·科奈特，法国演员、导演。",
        "type": "birth"
    },
    {
        "year": "1973",
        "content": "罗伯托·卡洛斯，巴西退役足球运动员。",
        "type": "birth"
    },
    {
        "year": "1975",
        "content": "叶山豪，日本籍香港演员。",
        "type": "birth"
    },
    {
        "year": "1975",
        "content": "大卫·哈伯，美国男演员。",
        "type": "birth"
    },
    {
        "year": "1976",
        "content": "杜诗梅，台湾女演员。",
        "type": "birth"
    },
    {
        "year": "1976",
        "content": "金善映，韩国女演员。",
        "type": "birth"
    },
    {
        "year": "1978",
        "content": "MC HotDog，台湾男歌手。",
        "type": "birth"
    },
    {
        "year": "1979",
        "content": "堂本刚，日本男艺人。",
        "type": "birth"
    },
    {
        "year": "1980",
        "content": "查理·亨南，英国男演员。",
        "type": "birth"
    },
    {
        "year": "1981",
        "content": "黄志玮，台湾男演员。",
        "type": "birth"
    },
    {
        "year": "1981",
        "content": "米高·彼特，美国男演员。",
        "type": "birth"
    },
    {
        "year": "1983",
        "content": "余苑绮，台湾演员、歌手。（2022年逝世）",
        "type": "birth"
    },
    {
        "year": "1983",
        "content": "郑智麟，韩裔美国女演员。",
        "type": "birth"
    },
    {
        "year": "1984",
        "content": "笠间淳，日本男性声优。",
        "type": "birth"
    },
    {
        "year": "1984",
        "content": "林素英，韩国女演员。",
        "type": "birth"
    },
    {
        "year": "1984",
        "content": "曼迪·穆尔，美国女歌手、演员。",
        "type": "birth"
    },
    {
        "year": "1985",
        "content": "王蒙，中国女子短道速滑运动员。",
        "type": "birth"
    },
    {
        "year": "1985",
        "content": "巴克哈德·阿卜迪，索马里裔美国男演员。",
        "type": "birth"
    },
    {
        "year": "1986",
        "content": "郑恩宇，韩国男演员。",
        "type": "birth"
    },
    {
        "year": "1986",
        "content": "申贤彬，韩国女演员。",
        "type": "birth"
    },
    {
        "year": "1986",
        "content": "艾伊莎·塔基亚，印度女演员。",
        "type": "birth"
    },
    {
        "year": "1987",
        "content": "张榕容，台湾女演员。",
        "type": "birth"
    },
    {
        "year": "1987",
        "content": "何泓姗，中国女演员。",
        "type": "birth"
    },
    {
        "year": "1987",
        "content": "钟蕙芝，香港少女模特儿。",
        "type": "birth"
    },
    {
        "year": "1987",
        "content": "水卜麻美，日本女性播报员。",
        "type": "birth"
    },
    {
        "year": "1987",
        "content": "海莉·薇思特拉，纽西兰跨界女高音、歌曲作家。",
        "type": "birth"
    },
    {
        "year": "1988",
        "content": "哈利·乔·奥斯蒙，美国男演员。",
        "type": "birth"
    },
    {
        "year": "1988",
        "content": "杨明纶，香港骑师。",
        "type": "birth"
    },
    {
        "year": "1989",
        "content": "华千涵，台湾女演员。",
        "type": "birth"
    },
    {
        "year": "1989",
        "content": "婉娜拉·宋提查，泰国女演员。",
        "type": "birth"
    },
    {
        "year": "1990",
        "content": "阿悄，中国女歌手。",
        "type": "birth"
    },
    {
        "year": "1990",
        "content": "亚历克斯·帕蒂弗，英国演员。",
        "type": "birth"
    },
    {
        "year": "1990",
        "content": "玛伦·莫里斯，美国女歌手、词曲作家、音乐制作人。",
        "type": "birth"
    },
    {
        "year": "1991",
        "content": "AJ·蜜雪卡，美国女演员。",
        "type": "birth"
    },
    {
        "year": "1992",
        "content": "黛西·蕾德莉，英国女演员。",
        "type": "birth"
    },
    {
        "year": "1993",
        "content": "陈泇彤，马来西亚Youtuber、电台主持人。",
        "type": "birth"
    },
    {
        "year": "1993",
        "content": "井上尚弥，日本职业拳击运动员。",
        "type": "birth"
    },
    {
        "year": "1993",
        "content": "索菲娅·卡森，美国女演员、歌手。",
        "type": "birth"
    },
    {
        "year": "1995",
        "content": "千春，日本女性声优。",
        "type": "birth"
    },
    {
        "year": "1996",
        "content": "黑泽朋世，日本女性声优。",
        "type": "birth"
    },
    {
        "year": "2000",
        "content": "温庆运，中华人民共和国死刑犯，广州天河驾车撞人事件肇事犯人。（2024年逝世）",
        "type": "birth"
    },
    {
        "year": "生不详",
        "content": "仓持若菜，日本女性声优。",
        "type": "birth"
    },
    {
        "year": "258",
        "content": "诸葛诞，中国三国时代曹魏后期重要将领。",
        "type": "death"
    },
    {
        "year": "879",
        "content": "路易二世，西法兰克国王。（846年出生）",
        "type": "death"
    },
    {
        "year": "1216",
        "content": "埃里克十世，瑞典国王。（1180年出生）",
        "type": "death"
    },
    {
        "year": "1347",
        "content": "奥卡姆的威廉，英国逻辑学家。（约1287年出生）",
        "type": "death"
    },
    {
        "year": "1533",
        "content": "弗雷德里克一世，丹麦国王和挪威国王。（1471年出生）",
        "type": "death"
    },
    {
        "year": "1585",
        "content": "教宗额我略十三世，罗马主教。（1502年出生）",
        "type": "death"
    },
    {
        "year": "1599",
        "content": "嘉百丽·戴斯特雷，法国国王亨利四世的情妇。（1573年出生）",
        "type": "death"
    },
    {
        "year": "1813",
        "content": "约瑟夫·拉格朗日，法国数学家、天文学家。（1736年出生）",
        "type": "death"
    },
    {
        "year": "1904",
        "content": "伊莎贝拉二世，西班牙女王。（1830年出生）",
        "type": "death"
    },
    {
        "year": "1906",
        "content": "乔治·加邦，1905年俄国革命领袖。（1870年出生）",
        "type": "death"
    },
    {
        "year": "1911",
        "content": "萨姆·劳埃德，美国智力游戏设计师、趣味数学家。（1841年出生）",
        "type": "death"
    },
    {
        "year": "1975",
        "content": "沃克·埃文斯，美国摄影师、摄影记者。（1903年出生）",
        "type": "death"
    },
    {
        "year": "1993",
        "content": "克里斯·哈（英语：Chris Hani），南非共产党总书记、非洲人国民大会军事组织“民族之矛”前参谋长。（1942年出生）",
        "type": "death"
    },
    {
        "year": "1995",
        "content": "陈云，中华人民共和国政治人物，中国共产党第一和第二代中央领导集体重要成员之一。（1905年出生）",
        "type": "death"
    },
    {
        "year": "2001",
        "content": "诺拉·爱丁顿（英语：Nora Eddington），美国女演员。（1924年出生）",
        "type": "death"
    },
    {
        "year": "2002",
        "content": "百武裕司，日本业余天文学家。（1950年出生）",
        "type": "death"
    },
    {
        "year": "2005",
        "content": "陈逸飞，中国油画家、视觉艺术家、电影导演。（1946年出生）",
        "type": "death"
    },
    {
        "year": "2010",
        "content": "莱赫·卡钦斯基，波兰政治人物，前任波兰总统。（1949年出生）",
        "type": "death"
    },
    {
        "year": "2013",
        "content": "罗伯特·G·爱德华兹，英国生理学家，因开发体外人工受精技术的成就被授予2010年诺贝尔生理学或医学奖。（1925年出生）",
        "type": "death"
    },
    {
        "year": "2015",
        "content": "溥任，中国末代皇帝宣统帝溥仪的四弟。（1918年出生）",
        "type": "death"
    },
    {
        "year": "2020",
        "content": "大林宣彦，日本电影导演。（1938年出生）",
        "type": "death"
    },
    {
        "year": "2024",
        "content": "大卫·古德斯坦，美国物理学家、教育家。（1939年出生）",
        "type": "death"
    },
    {
        "year": "2024",
        "content": "O·J·辛普森，美国职业美式足球运动员、演员。（1947年出生）",
        "type": "death"
    }
]